generate_kat_core/__init__.py
generate_kat_core/algorithm_validator.py
generate_kat_core/arguments_configuration.py
generate_kat_core/autorepr.py
generate_kat_core/file_helper.py
generate_kat_core/file_utils.py
generate_kat_core/general_parsing.py
generate_kat_core/kat_generation.py
generate_kat_core/kat_printer.py
generate_kat_core/kat_verification.py
generate_kat_core/primitive_browser.py
generate_kat_core/py.typed
generate_kat_core/utils.py
generate_kat_core/test/__init__.py
generate_kat_core/test/generate_test_helper.py
generate_kat_core/test/verify_test_helper.py
generate_kat_core-0.0.6.dist-info/METADATA
generate_kat_core-0.0.6.dist-info/WHEEL
generate_kat_core-0.0.6.dist-info/top_level.txt
generate_kat_core-0.0.6.dist-info/RECORD
